{
  "data": [
    {
      "id": "8926-586",
      "type": "drop",
      "attributes": {
        "members": true,
        "drop_requirements": null,
        "noted": false,
        "quantity_min": 1,
        "quantity_max": null,
        "rarity": "0.0234375"
      },
      "meta": {
        "item_name": "Bandana eyepatch (blue)",
        "monster_name": "Zombie pirate (25)"
      }
    },
    {
      "id": "8926-584",
      "type": "drop",
      "attributes": {
        "members": true,
        "drop_requirements": null,
        "noted": false,
        "quantity_min": 1,
        "quantity_max": null,
        "rarity": "0.0234375"
      },
      "meta": {
        "item_name": "Bandana eyepatch (blue)",
        "monster_name": "Zombie pirate (24)"
      }
    },
    {
      "id": "8926-582",
      "type": "drop",
      "attributes": {
        "members": true,
        "drop_requirements": null,
        "noted": false,
        "quantity_min": 1,
        "quantity_max": null,
        "rarity": "0.0234375"
      },
      "meta": {
        "item_name": "Bandana eyepatch (blue)",
        "monster_name": "Zombie pirate (23)"
      }
    },
    {
      "id": "8926-581",
      "type": "drop",
      "attributes": {
        "members": true,
        "drop_requirements": null,
        "noted": false,
        "quantity_min": 1,
        "quantity_max": null,
        "rarity": "0.0234375"
      },
      "meta": {
        "item_name": "Bandana eyepatch (blue)",
        "monster_name": "Zombie pirate (22)"
      }
    },
    {
      "id": "8926-579",
      "type": "drop",
      "attributes": {
        "members": true,
        "drop_requirements": null,
        "noted": false,
        "quantity_min": 1,
        "quantity_max": null,
        "rarity": "0.0234375"
      },
      "meta": {
        "item_name": "Bandana eyepatch (blue)",
        "monster_name": "Zombie pirate (20)"
      }
    },
    {
      "id": "8926-578",
      "type": "drop",
      "attributes": {
        "members": true,
        "drop_requirements": null,
        "noted": false,
        "quantity_min": 1,
        "quantity_max": null,
        "rarity": "0.0234375"
      },
      "meta": {
        "item_name": "Bandana eyepatch (blue)",
        "monster_name": "Zombie pirate (19)"
      }
    },
    {
      "id": "8926-577",
      "type": "drop",
      "attributes": {
        "members": true,
        "drop_requirements": null,
        "noted": false,
        "quantity_min": 1,
        "quantity_max": null,
        "rarity": "0.0234375"
      },
      "meta": {
        "item_name": "Bandana eyepatch (blue)",
        "monster_name": "Zombie pirate (18)"
      }
    },
    {
      "id": "8926-576",
      "type": "drop",
      "attributes": {
        "members": true,
        "drop_requirements": null,
        "noted": false,
        "quantity_min": 1,
        "quantity_max": null,
        "rarity": "0.0234375"
      },
      "meta": {
        "item_name": "Bandana eyepatch (blue)",
        "monster_name": "Zombie pirate (1)"
      }
    },
    {
      "id": "8926-575",
      "type": "drop",
      "attributes": {
        "members": true,
        "drop_requirements": null,
        "noted": false,
        "quantity_min": 1,
        "quantity_max": null,
        "rarity": "0.0234375"
      },
      "meta": {
        "item_name": "Bandana eyepatch (blue)",
        "monster_name": "Zombie pirate (17)"
      }
    },
    {
      "id": "8926-574",
      "type": "drop",
      "attributes": {
        "members": true,
        "drop_requirements": null,
        "noted": false,
        "quantity_min": 1,
        "quantity_max": null,
        "rarity": "0.0234375"
      },
      "meta": {
        "item_name": "Bandana eyepatch (blue)",
        "monster_name": "Zombie pirate (15)"
      }
    },
    {
      "id": "8926-573",
      "type": "drop",
      "attributes": {
        "members": true,
        "drop_requirements": null,
        "noted": false,
        "quantity_min": 1,
        "quantity_max": null,
        "rarity": "0.0234375"
      },
      "meta": {
        "item_name": "Bandana eyepatch (blue)",
        "monster_name": "Zombie pirate (14)"
      }
    },
    {
      "id": "8926-572",
      "type": "drop",
      "attributes": {
        "members": true,
        "drop_requirements": null,
        "noted": false,
        "quantity_min": 1,
        "quantity_max": null,
        "rarity": "0.0234375"
      },
      "meta": {
        "item_name": "Bandana eyepatch (blue)",
        "monster_name": "Zombie pirate (13)"
      }
    },
    {
      "id": "8926-571",
      "type": "drop",
      "attributes": {
        "members": true,
        "drop_requirements": null,
        "noted": false,
        "quantity_min": 1,
        "quantity_max": null,
        "rarity": "0.0234375"
      },
      "meta": {
        "item_name": "Bandana eyepatch (blue)",
        "monster_name": "Zombie pirate (12)"
      }
    },
    {
      "id": "8926-569",
      "type": "drop",
      "attributes": {
        "members": true,
        "drop_requirements": null,
        "noted": false,
        "quantity_min": 1,
        "quantity_max": null,
        "rarity": "0.0234375"
      },
      "meta": {
        "item_name": "Bandana eyepatch (blue)",
        "monster_name": "Zombie pirate (11)"
      }
    },
    {
      "id": "8926-568",
      "type": "drop",
      "attributes": {
        "members": true,
        "drop_requirements": null,
        "noted": false,
        "quantity_min": 1,
        "quantity_max": null,
        "rarity": "0.0234375"
      },
      "meta": {
        "item_name": "Bandana eyepatch (blue)",
        "monster_name": "Zombie pirate (10)"
      }
    },
    {
      "id": "8926-567",
      "type": "drop",
      "attributes": {
        "members": true,
        "drop_requirements": null,
        "noted": false,
        "quantity_min": 1,
        "quantity_max": null,
        "rarity": "0.0234375"
      },
      "meta": {
        "item_name": "Bandana eyepatch (blue)",
        "monster_name": "Zombie pirate (9)"
      }
    },
    {
      "id": "8926-565",
      "type": "drop",
      "attributes": {
        "members": true,
        "drop_requirements": null,
        "noted": false,
        "quantity_min": 1,
        "quantity_max": null,
        "rarity": "0.0234375"
      },
      "meta": {
        "item_name": "Bandana eyepatch (blue)",
        "monster_name": "Zombie pirate (8)"
      }
    },
    {
      "id": "8926-563",
      "type": "drop",
      "attributes": {
        "members": true,
        "drop_requirements": null,
        "noted": false,
        "quantity_min": 1,
        "quantity_max": null,
        "rarity": "0.0234375"
      },
      "meta": {
        "item_name": "Bandana eyepatch (blue)",
        "monster_name": "Zombie pirate (7)"
      }
    },
    {
      "id": "8926-561",
      "type": "drop",
      "attributes": {
        "members": true,
        "drop_requirements": null,
        "noted": false,
        "quantity_min": 1,
        "quantity_max": null,
        "rarity": "0.0234375"
      },
      "meta": {
        "item_name": "Bandana eyepatch (blue)",
        "monster_name": "Sorebones"
      }
    },
    {
      "id": "8926-614",
      "type": "drop",
      "attributes": {
        "members": true,
        "drop_requirements": null,
        "noted": false,
        "quantity_min": 1,
        "quantity_max": null,
        "rarity": "0.0234375"
      },
      "meta": {
        "item_name": "Bandana eyepatch (blue)",
        "monster_name": "Zombie pirate (2)"
      }
    },
    {
      "id": "8926-580",
      "type": "drop",
      "attributes": {
        "members": true,
        "drop_requirements": null,
        "noted": false,
        "quantity_min": 1,
        "quantity_max": null,
        "rarity": "0.0234375"
      },
      "meta": {
        "item_name": "Bandana eyepatch (blue)",
        "monster_name": "Zombie pirate (21)"
      }
    },
    {
      "id": "8926-615",
      "type": "drop",
      "attributes": {
        "members": true,
        "drop_requirements": null,
        "noted": false,
        "quantity_min": 1,
        "quantity_max": null,
        "rarity": "0.0234375"
      },
      "meta": {
        "item_name": "Bandana eyepatch (blue)",
        "monster_name": "Zombie pirate (3)"
      }
    },
    {
      "id": "8926-616",
      "type": "drop",
      "attributes": {
        "members": true,
        "drop_requirements": null,
        "noted": false,
        "quantity_min": 1,
        "quantity_max": null,
        "rarity": "0.0234375"
      },
      "meta": {
        "item_name": "Bandana eyepatch (blue)",
        "monster_name": "Zombie pirate (4)"
      }
    },
    {
      "id": "8926-617",
      "type": "drop",
      "attributes": {
        "members": true,
        "drop_requirements": null,
        "noted": false,
        "quantity_min": 1,
        "quantity_max": null,
        "rarity": "0.0234375"
      },
      "meta": {
        "item_name": "Bandana eyepatch (blue)",
        "monster_name": "Zombie pirate (5)"
      }
    },
    {
      "id": "8926-618",
      "type": "drop",
      "attributes": {
        "members": true,
        "drop_requirements": null,
        "noted": false,
        "quantity_min": 1,
        "quantity_max": null,
        "rarity": "0.0234375"
      },
      "meta": {
        "item_name": "Bandana eyepatch (blue)",
        "monster_name": "Zombie pirate (6)"
      }
    },
    {
      "id": "8926-595",
      "type": "drop",
      "attributes": {
        "members": true,
        "drop_requirements": null,
        "noted": false,
        "quantity_min": 1,
        "quantity_max": null,
        "rarity": "0.0234375"
      },
      "meta": {
        "item_name": "Bandana eyepatch (blue)",
        "monster_name": "Zombie pirate (30)"
      }
    },
    {
      "id": "8926-597",
      "type": "drop",
      "attributes": {
        "members": true,
        "drop_requirements": null,
        "noted": false,
        "quantity_min": 1,
        "quantity_max": null,
        "rarity": "0.0234375"
      },
      "meta": {
        "item_name": "Bandana eyepatch (blue)",
        "monster_name": "Zombie pirate (31)"
      }
    },
    {
      "id": "8926-599",
      "type": "drop",
      "attributes": {
        "members": true,
        "drop_requirements": null,
        "noted": false,
        "quantity_min": 1,
        "quantity_max": null,
        "rarity": "0.0234375"
      },
      "meta": {
        "item_name": "Bandana eyepatch (blue)",
        "monster_name": "Zombie pirate (32)"
      }
    },
    {
      "id": "8926-592",
      "type": "drop",
      "attributes": {
        "members": true,
        "drop_requirements": null,
        "noted": false,
        "quantity_min": 1,
        "quantity_max": null,
        "rarity": "0.0234375"
      },
      "meta": {
        "item_name": "Bandana eyepatch (blue)",
        "monster_name": "Zombie pirate (28)"
      }
    },
    {
      "id": "8926-590",
      "type": "drop",
      "attributes": {
        "members": true,
        "drop_requirements": null,
        "noted": false,
        "quantity_min": 1,
        "quantity_max": null,
        "rarity": "0.0234375"
      },
      "meta": {
        "item_name": "Bandana eyepatch (blue)",
        "monster_name": "Zombie pirate (27)"
      }
    },
    {
      "id": "8926-588",
      "type": "drop",
      "attributes": {
        "members": true,
        "drop_requirements": null,
        "noted": false,
        "quantity_min": 1,
        "quantity_max": null,
        "rarity": "0.0234375"
      },
      "meta": {
        "item_name": "Bandana eyepatch (blue)",
        "monster_name": "Zombie pirate (26)"
      }
    },
    {
      "id": "8926-593",
      "type": "drop",
      "attributes": {
        "members": true,
        "drop_requirements": null,
        "noted": false,
        "quantity_min": 1,
        "quantity_max": null,
        "rarity": "0.0234375"
      },
      "meta": {
        "item_name": "Bandana eyepatch (blue)",
        "monster_name": "Zombie pirate (29)"
      }
    }
  ]
}