{
  "data": [
    {
      "id": "10976-6504",
      "type": "drop",
      "attributes": {
        "members": true,
        "drop_requirements": null,
        "noted": false,
        "quantity_min": 1,
        "quantity_max": null,
        "rarity": "0.0025"
      },
      "meta": {
        "item_name": "Long bone",
        "monster_name": "Venenatis"
      }
    },
    {
      "id": "10977-6504",
      "type": "drop",
      "attributes": {
        "members": true,
        "drop_requirements": null,
        "noted": false,
        "quantity_min": 1,
        "quantity_max": null,
        "rarity": "0.000199501246882793"
      },
      "meta": {
        "item_name": "Curved bone",
        "monster_name": "Venenatis"
      }
    },
    {
      "id": "6685-6504",
      "type": "drop",
      "attributes": {
        "members": true,
        "drop_requirements": null,
        "noted": false,
        "quantity_min": 1,
        "quantity_max": null,
        "rarity": "0.333333333333333"
      },
      "meta": {
        "item_name": "Saradomin brew (4 dose)",
        "monster_name": "Venenatis"
      }
    },
    {
      "id": "6691-6504",
      "type": "drop",
      "attributes": {
        "members": true,
        "drop_requirements": null,
        "noted": false,
        "quantity_min": 1,
        "quantity_max": null,
        "rarity": "0.333333333333333"
      },
      "meta": {
        "item_name": "Saradomin brew (1 dose)",
        "monster_name": "Venenatis"
      }
    },
    {
      "id": "23490-6504",
      "type": "drop",
      "attributes": {
        "members": true,
        "drop_requirements": "krystilia-task-only",
        "noted": false,
        "quantity_min": 1,
        "quantity_max": null,
        "rarity": "0.02"
      },
      "meta": {
        "item_name": "Larran's key",
        "monster_name": "Venenatis"
      }
    },
    {
      "id": "21257-6504",
      "type": "drop",
      "attributes": {
        "members": true,
        "drop_requirements": "krystilia-task-only",
        "noted": false,
        "quantity_min": 1,
        "quantity_max": null,
        "rarity": "0.0333333333333333"
      },
      "meta": {
        "item_name": "Slayer's enchantment",
        "monster_name": "Venenatis"
      }
    },
    {
      "id": "9194-6504",
      "type": "drop",
      "attributes": {
        "members": true,
        "drop_requirements": null,
        "noted": false,
        "quantity_min": 60,
        "quantity_max": null,
        "rarity": "0.0390625"
      },
      "meta": {
        "item_name": "Onyx bolt tips",
        "monster_name": "Venenatis"
      }
    },
    {
      "id": "444-6504",
      "type": "drop",
      "attributes": {
        "members": true,
        "drop_requirements": null,
        "noted": true,
        "quantity_min": 300,
        "quantity_max": null,
        "rarity": "0.046875"
      },
      "meta": {
        "item_name": "Gold ore",
        "monster_name": "Venenatis"
      }
    },
    {
      "id": "1617-6504",
      "type": "drop",
      "attributes": {
        "members": true,
        "drop_requirements": null,
        "noted": true,
        "quantity_min": 10,
        "quantity_max": null,
        "rarity": "0.0546875"
      },
      "meta": {
        "item_name": "Uncut diamond",
        "monster_name": "Venenatis"
      }
    },
    {
      "id": "1619-6504",
      "type": "drop",
      "attributes": {
        "members": true,
        "drop_requirements": null,
        "noted": true,
        "quantity_min": 20,
        "quantity_max": null,
        "rarity": "0.0546875"
      },
      "meta": {
        "item_name": "Uncut ruby",
        "monster_name": "Venenatis"
      }
    },
    {
      "id": "2-6504",
      "type": "drop",
      "attributes": {
        "members": true,
        "drop_requirements": null,
        "noted": false,
        "quantity_min": 250,
        "quantity_max": null,
        "rarity": "0.03125"
      },
      "meta": {
        "item_name": "Cannonball",
        "monster_name": "Venenatis"
      }
    },
    {
      "id": "9243-6504",
      "type": "drop",
      "attributes": {
        "members": true,
        "drop_requirements": null,
        "noted": false,
        "quantity_min": 100,
        "quantity_max": null,
        "rarity": "0.0390625"
      },
      "meta": {
        "item_name": "Diamond bolts (e)",
        "monster_name": "Venenatis"
      }
    },
    {
      "id": "565-6504",
      "type": "drop",
      "attributes": {
        "members": true,
        "drop_requirements": null,
        "noted": false,
        "quantity_min": 200,
        "quantity_max": null,
        "rarity": "0.0546875"
      },
      "meta": {
        "item_name": "Blood rune (Regular)",
        "monster_name": "Venenatis"
      }
    },
    {
      "id": "560-6504",
      "type": "drop",
      "attributes": {
        "members": true,
        "drop_requirements": null,
        "noted": false,
        "quantity_min": 300,
        "quantity_max": null,
        "rarity": "0.0546875"
      },
      "meta": {
        "item_name": "Death rune (Regular)",
        "monster_name": "Venenatis"
      }
    },
    {
      "id": "562-6504",
      "type": "drop",
      "attributes": {
        "members": true,
        "drop_requirements": null,
        "noted": false,
        "quantity_min": 400,
        "quantity_max": null,
        "rarity": "0.0546875"
      },
      "meta": {
        "item_name": "Chaos rune (Regular)",
        "monster_name": "Venenatis"
      }
    },
    {
      "id": "7158-6504",
      "type": "drop",
      "attributes": {
        "members": true,
        "drop_requirements": null,
        "noted": false,
        "quantity_min": 1,
        "quantity_max": null,
        "rarity": "0.00390625"
      },
      "meta": {
        "item_name": "Dragon 2h sword",
        "monster_name": "Venenatis"
      }
    },
    {
      "id": "11920-6504",
      "type": "drop",
      "attributes": {
        "members": true,
        "drop_requirements": null,
        "noted": false,
        "quantity_min": 1,
        "quantity_max": null,
        "rarity": "0.005859375"
      },
      "meta": {
        "item_name": "Dragon pickaxe",
        "monster_name": "Venenatis"
      }
    },
    {
      "id": "1319-6504",
      "type": "drop",
      "attributes": {
        "members": true,
        "drop_requirements": null,
        "noted": false,
        "quantity_min": 1,
        "quantity_max": null,
        "rarity": "0.0234375"
      },
      "meta": {
        "item_name": "Rune 2h sword",
        "monster_name": "Venenatis"
      }
    },
    {
      "id": "868-6504",
      "type": "drop",
      "attributes": {
        "members": true,
        "drop_requirements": null,
        "noted": false,
        "quantity_min": 60,
        "quantity_max": null,
        "rarity": "0.0390625"
      },
      "meta": {
        "item_name": "Rune knife (Unpoisoned)",
        "monster_name": "Venenatis"
      }
    },
    {
      "id": "1275-6504",
      "type": "drop",
      "attributes": {
        "members": true,
        "drop_requirements": null,
        "noted": false,
        "quantity_min": 1,
        "quantity_max": null,
        "rarity": "0.09375"
      },
      "meta": {
        "item_name": "Rune pickaxe (Regular)",
        "monster_name": "Venenatis"
      }
    },
    {
      "id": "12605-6504",
      "type": "drop",
      "attributes": {
        "members": true,
        "drop_requirements": null,
        "noted": false,
        "quantity_min": 1,
        "quantity_max": null,
        "rarity": "0.001953125"
      },
      "meta": {
        "item_name": "Treasonous ring",
        "monster_name": "Venenatis"
      }
    },
    {
      "id": "1513-6504",
      "type": "drop",
      "attributes": {
        "members": true,
        "drop_requirements": null,
        "noted": true,
        "quantity_min": 100,
        "quantity_max": null,
        "rarity": "0.0390625"
      },
      "meta": {
        "item_name": "Magic logs",
        "monster_name": "Venenatis"
      }
    },
    {
      "id": "225-6504",
      "type": "drop",
      "attributes": {
        "members": true,
        "drop_requirements": null,
        "noted": true,
        "quantity_min": 25,
        "quantity_max": null,
        "rarity": "0.0390625"
      },
      "meta": {
        "item_name": "Limpwurt root",
        "monster_name": "Venenatis"
      }
    },
    {
      "id": "223-6504",
      "type": "drop",
      "attributes": {
        "members": true,
        "drop_requirements": null,
        "noted": true,
        "quantity_min": 500,
        "quantity_max": null,
        "rarity": "0.0234375"
      },
      "meta": {
        "item_name": "Red spiders' eggs",
        "monster_name": "Venenatis"
      }
    },
    {
      "id": "237-6504",
      "type": "drop",
      "attributes": {
        "members": true,
        "drop_requirements": null,
        "noted": true,
        "quantity_min": 100,
        "quantity_max": null,
        "rarity": "0.015625"
      },
      "meta": {
        "item_name": "Unicorn horn",
        "monster_name": "Venenatis"
      }
    },
    {
      "id": "1631-6504",
      "type": "drop",
      "attributes": {
        "members": true,
        "drop_requirements": null,
        "noted": false,
        "quantity_min": 1,
        "quantity_max": null,
        "rarity": "0.015625"
      },
      "meta": {
        "item_name": "Uncut dragonstone",
        "monster_name": "Venenatis"
      }
    },
    {
      "id": "3051-6504",
      "type": "drop",
      "attributes": {
        "members": true,
        "drop_requirements": null,
        "noted": true,
        "quantity_min": 100,
        "quantity_max": null,
        "rarity": "0.0078125"
      },
      "meta": {
        "item_name": "Grimy snapdragon",
        "monster_name": "Venenatis"
      }
    },
    {
      "id": "11936-6504",
      "type": "drop",
      "attributes": {
        "members": true,
        "drop_requirements": null,
        "noted": false,
        "quantity_min": 8,
        "quantity_max": null,
        "rarity": "0.078125"
      },
      "meta": {
        "item_name": "Dark crab",
        "monster_name": "Venenatis"
      }
    },
    {
      "id": "3024-6504",
      "type": "drop",
      "attributes": {
        "members": true,
        "drop_requirements": null,
        "noted": false,
        "quantity_min": 3,
        "quantity_max": null,
        "rarity": "0.078125"
      },
      "meta": {
        "item_name": "Super restore (4 dose)",
        "monster_name": "Venenatis"
      }
    },
    {
      "id": "6034-6504",
      "type": "drop",
      "attributes": {
        "members": true,
        "drop_requirements": null,
        "noted": true,
        "quantity_min": 100,
        "quantity_max": null,
        "rarity": "0.037109375"
      },
      "meta": {
        "item_name": "Supercompost",
        "monster_name": "Venenatis"
      }
    },
    {
      "id": "5952-6504",
      "type": "drop",
      "attributes": {
        "members": true,
        "drop_requirements": null,
        "noted": true,
        "quantity_min": 10,
        "quantity_max": null,
        "rarity": "0.0234375"
      },
      "meta": {
        "item_name": "Antidote++ (4 dose)",
        "monster_name": "Venenatis"
      }
    },
    {
      "id": "11940-6504",
      "type": "drop",
      "attributes": {
        "members": true,
        "drop_requirements": null,
        "noted": false,
        "quantity_min": 375,
        "quantity_max": null,
        "rarity": "0.0078125"
      },
      "meta": {
        "item_name": "Dark fishing bait",
        "monster_name": "Venenatis"
      }
    },
    {
      "id": "5315-6504",
      "type": "drop",
      "attributes": {
        "members": true,
        "drop_requirements": null,
        "noted": false,
        "quantity_min": 1,
        "quantity_max": null,
        "rarity": "0.0078125"
      },
      "meta": {
        "item_name": "Yew seed",
        "monster_name": "Venenatis"
      }
    },
    {
      "id": "5316-6504",
      "type": "drop",
      "attributes": {
        "members": true,
        "drop_requirements": null,
        "noted": false,
        "quantity_min": 1,
        "quantity_max": null,
        "rarity": "0.0078125"
      },
      "meta": {
        "item_name": "Magic seed",
        "monster_name": "Venenatis"
      }
    },
    {
      "id": "5289-6504",
      "type": "drop",
      "attributes": {
        "members": true,
        "drop_requirements": null,
        "noted": false,
        "quantity_min": 1,
        "quantity_max": null,
        "rarity": "0.0078125"
      },
      "meta": {
        "item_name": "Palm tree seed",
        "monster_name": "Venenatis"
      }
    },
    {
      "id": "11941-6504",
      "type": "drop",
      "attributes": {
        "members": true,
        "drop_requirements": null,
        "noted": false,
        "quantity_min": 1,
        "quantity_max": null,
        "rarity": "0.333333333333333"
      },
      "meta": {
        "item_name": "Looting bag (Closed)",
        "monster_name": "Venenatis"
      }
    },
    {
      "id": "23083-6504",
      "type": "drop",
      "attributes": {
        "members": true,
        "drop_requirements": null,
        "noted": false,
        "quantity_min": 1,
        "quantity_max": null,
        "rarity": "0.036764705882353"
      },
      "meta": {
        "item_name": "Brimstone key",
        "monster_name": "Venenatis"
      }
    },
    {
      "id": "12073-6504",
      "type": "drop",
      "attributes": {
        "members": true,
        "drop_requirements": null,
        "noted": false,
        "quantity_min": 1,
        "quantity_max": null,
        "rarity": "0.01"
      },
      "meta": {
        "item_name": "Clue scroll (elite)",
        "monster_name": "Venenatis"
      }
    },
    {
      "id": "13177-6504",
      "type": "drop",
      "attributes": {
        "members": true,
        "drop_requirements": null,
        "noted": false,
        "quantity_min": 1,
        "quantity_max": null,
        "rarity": "0.0005"
      },
      "meta": {
        "item_name": "Venenatis spiderling",
        "monster_name": "Venenatis"
      }
    },
    {
      "id": "995-6504",
      "type": "drop",
      "attributes": {
        "members": true,
        "drop_requirements": null,
        "noted": false,
        "quantity_min": 15000,
        "quantity_max": 19999,
        "rarity": "0.1484375"
      },
      "meta": {
        "item_name": "Coins",
        "monster_name": "Venenatis"
      }
    }
  ]
}