{
  "data": [
    {
      "id": "1635-450",
      "type": "drop",
      "attributes": {
        "members": true,
        "drop_requirements": null,
        "noted": false,
        "quantity_min": 1,
        "quantity_max": null,
        "rarity": "0.0234375"
      },
      "meta": {
        "item_name": "Gold ring",
        "monster_name": "Crawling Hand (Level 7)"
      }
    },
    {
      "id": "7975-450",
      "type": "drop",
      "attributes": {
        "members": true,
        "drop_requirements": null,
        "noted": false,
        "quantity_min": 1,
        "quantity_max": null,
        "rarity": "0.002"
      },
      "meta": {
        "item_name": "Crawling hand (item)",
        "monster_name": "Crawling Hand (Level 7)"
      }
    },
    {
      "id": "2932-450",
      "type": "drop",
      "attributes": {
        "members": true,
        "drop_requirements": null,
        "noted": false,
        "quantity_min": 1,
        "quantity_max": null,
        "rarity": "0.015625"
      },
      "meta": {
        "item_name": "Teal gloves",
        "monster_name": "Crawling Hand (Level 7)"
      }
    },
    {
      "id": "2912-450",
      "type": "drop",
      "attributes": {
        "members": true,
        "drop_requirements": null,
        "noted": false,
        "quantity_min": 1,
        "quantity_max": null,
        "rarity": "0.015625"
      },
      "meta": {
        "item_name": "Red gloves",
        "monster_name": "Crawling Hand (Level 7)"
      }
    },
    {
      "id": "2942-450",
      "type": "drop",
      "attributes": {
        "members": true,
        "drop_requirements": null,
        "noted": false,
        "quantity_min": 1,
        "quantity_max": null,
        "rarity": "0.015625"
      },
      "meta": {
        "item_name": "Purple gloves",
        "monster_name": "Crawling Hand (Level 7)"
      }
    },
    {
      "id": "2922-450",
      "type": "drop",
      "attributes": {
        "members": true,
        "drop_requirements": null,
        "noted": false,
        "quantity_min": 1,
        "quantity_max": null,
        "rarity": "0.015625"
      },
      "meta": {
        "item_name": "Yellow gloves",
        "monster_name": "Crawling Hand (Level 7)"
      }
    },
    {
      "id": "1059-450",
      "type": "drop",
      "attributes": {
        "members": true,
        "drop_requirements": null,
        "noted": false,
        "quantity_min": 1,
        "quantity_max": null,
        "rarity": "0.1640625"
      },
      "meta": {
        "item_name": "Leather gloves",
        "monster_name": "Crawling Hand (Level 7)"
      }
    },
    {
      "id": "526-450",
      "type": "drop",
      "attributes": {
        "members": true,
        "drop_requirements": null,
        "noted": false,
        "quantity_min": 1,
        "quantity_max": null,
        "rarity": "1.0"
      },
      "meta": {
        "item_name": "Bones",
        "monster_name": "Crawling Hand (Level 7)"
      }
    },
    {
      "id": "1639-450",
      "type": "drop",
      "attributes": {
        "members": true,
        "drop_requirements": null,
        "noted": false,
        "quantity_min": 1,
        "quantity_max": null,
        "rarity": "0.015625"
      },
      "meta": {
        "item_name": "Emerald ring",
        "monster_name": "Crawling Hand (Level 7)"
      }
    },
    {
      "id": "1637-450",
      "type": "drop",
      "attributes": {
        "members": true,
        "drop_requirements": null,
        "noted": false,
        "quantity_min": 1,
        "quantity_max": null,
        "rarity": "0.015625"
      },
      "meta": {
        "item_name": "Sapphire ring",
        "monster_name": "Crawling Hand (Level 7)"
      }
    },
    {
      "id": "995-450",
      "type": "drop",
      "attributes": {
        "members": true,
        "drop_requirements": null,
        "noted": false,
        "quantity_min": 5,
        "quantity_max": null,
        "rarity": "0.1640625"
      },
      "meta": {
        "item_name": "Coins",
        "monster_name": "Crawling Hand (Level 7)"
      }
    },
    {
      "id": "995-450",
      "type": "drop",
      "attributes": {
        "members": true,
        "drop_requirements": null,
        "noted": false,
        "quantity_min": 8,
        "quantity_max": null,
        "rarity": "0.1796875"
      },
      "meta": {
        "item_name": "Coins",
        "monster_name": "Crawling Hand (Level 7)"
      }
    }
  ]
}